monsterapi/Dreambooth_config.py
monsterapi/InputDataModels.py
monsterapi/LLM_config.py
monsterapi/LLamaIndexClient.py
monsterapi/Whisper_config.py
monsterapi/__init__.py
monsterapi/client.py
monsterapi/deployDataModels.py
monsterapi/nextGenLLMClient.py
monsterapi/utils.py
monsterapi/benchmark/LLMBenchMark.py
monsterapi/benchmark/__init__.py
monsterapi-1.0.9.3.dist-info/LICENSE
monsterapi-1.0.9.3.dist-info/METADATA
monsterapi-1.0.9.3.dist-info/WHEEL
monsterapi-1.0.9.3.dist-info/top_level.txt
monsterapi-1.0.9.3.dist-info/RECORD
