Metadata-Version: 2.1
Name: monsterapi
Version: 1.0.9.3
Summary: A Python client for Monster API v2
Home-page: https://github.com/qblocks/monsterapiclient
Author: Ramachandra Vikas Chamarthi
Author-email: vikas@qblocks.cloud
Classifier: Programming Language :: Python :: 3
Classifier: License :: OSI Approved :: Apache Software License
Classifier: Operating System :: OS Independent
Requires-Python: >=3.6
License-File: LICENSE
Requires-Dist: requests
Requires-Dist: requests-toolbelt
Requires-Dist: pydantic
Provides-Extra: tests
Requires-Dist: pytest; extra == "tests"
Requires-Dist: unittest.mock; python_version < "3.3" and extra == "tests"
